docs/source/conf.py
tests/centroidspng2csv_test.py
tests/conf_matrix_sum_test.py
tests/cpairs_test.py
tests/example_test.py
tests/generate_centroids.py
tests/generate_rswoosh.py
tests/get_conn_comp_test.py
tests/graph2centroids_test.py
tests/graph_idx_test.py
tests/hov_prob_pipe_test.py
tests/hov_prob_test.py
tests/metrics_pairs_test.py
tests/metrics_test.py
tests/png2graph_test.py
tests/pngcsv2geojson_test.py
tests/pngcsv2graph_test.py
tests/read_nodes_test.py
tests/remove_idx_test.py
tests/rswoosh_test.py
tests/tda_test.py
tumourkit/__init__.py
tumourkit/eval_pipe.py
tumourkit/infer_pipe.py
tumourkit/make_dirs.py
tumourkit/research_pipe.py
tumourkit/train_pipe.py
tumourkit/classification/__init__.py
tumourkit/classification/compute_imbalance.py
tumourkit/classification/evaluate.py
tumourkit/classification/infer.py
tumourkit/classification/read_graph.py
tumourkit/classification/train_graphs.py
tumourkit/classification/train_xgboost.py
tumourkit/classification/models/__init__.py
tumourkit/classification/models/gat.py
tumourkit/classification/models/gcn.py
tumourkit/classification/models/gin.py
tumourkit/classification/models/graphsage.py
tumourkit/classification/models/hgao.py
tumourkit/classification/models/norm.py
tumourkit/demo/app.py
tumourkit/postprocessing/__init__.py
tumourkit/postprocessing/compare_barcodes.py
tumourkit/postprocessing/draw_barcode.py
tumourkit/postprocessing/draw_cells.py
tumourkit/postprocessing/draw_graph.py
tumourkit/postprocessing/draw_rips.py
tumourkit/postprocessing/extract_tensorboard.py
tumourkit/postprocessing/join_graph_gt.py
tumourkit/postprocessing/join_hovprob_graph.py
tumourkit/postprocessing/merge_cells.py
tumourkit/postprocessing/plot_logs.py
tumourkit/postprocessing/rswoosh.py
tumourkit/postprocessing/summarize_logs.py
tumourkit/preprocessing/__init__.py
tumourkit/preprocessing/centroids2png.py
tumourkit/preprocessing/centroidspng2csv.py
tumourkit/preprocessing/geojson2pngcsv.py
tumourkit/preprocessing/graph2centroids.py
tumourkit-0.10.1.dist-info/licenses/LICENSE
tumourkit-0.10.1.dist-info/METADATA
tumourkit-0.10.1.dist-info/WHEEL
tumourkit-0.10.1.dist-info/entry_points.txt
tumourkit-0.10.1.dist-info/top_level.txt
tumourkit-0.10.1.dist-info/RECORD
