Metadata-Version: 2.4
Name: tumourkit
Version: 0.10.1
Summary: A SDK for tumour study
Author-email: Jose Pérez Cano <joseperez2000@hotmail.es>
License:                     GNU AFFERO GENERAL PUBLIC LICENSE
Classifier: Development Status :: 2 - Pre-Alpha
Classifier: Environment :: GPU :: NVIDIA CUDA :: 11.7
Classifier: Environment :: Console
Classifier: Intended Audience :: Healthcare Industry
Classifier: Intended Audience :: Developers
Classifier: Intended Audience :: Science/Research
Classifier: License :: OSI Approved :: GNU Affero General Public License v3
Classifier: Natural Language :: English
Classifier: Operating System :: MacOS
Classifier: Operating System :: POSIX :: Linux
Classifier: Operating System :: Microsoft :: Windows
Classifier: Programming Language :: Python :: 3.8
Classifier: Programming Language :: Python :: 3.9
Classifier: Programming Language :: Python :: 3.10
Classifier: Typing :: Stubs Only
Requires-Python: >=3.8
License-File: LICENSE
Requires-Dist: attrs==22.2.0
Requires-Dist: altair==5.0.1
Requires-Dist: vl-convert-python
Requires-Dist: beautifulsoup4==4.12.2
Requires-Dist: certifi==2022.12.7
Requires-Dist: charset-normalizer==3.0.1
Requires-Dist: contourpy==1.0.7
Requires-Dist: cycler==0.11.0
Requires-Dist: docopt==0.6.2
Requires-Dist: exceptiongroup==1.1.0
Requires-Dist: flake8==6.0.0
Requires-Dist: fonttools==4.38.0
Requires-Dist: geojson==2.5.0
Requires-Dist: gradio==3.26.0
Requires-Dist: gudhi==3.11.0
Requires-Dist: idna==3.4
Requires-Dist: imageio==2.24.0
Requires-Dist: iniconfig==2.0.0
Requires-Dist: joblib==1.2.0
Requires-Dist: kiwisolver==1.4.4
Requires-Dist: matplotlib==3.6.3
Requires-Dist: mccabe==0.7.0
Requires-Dist: networkx==3.0
Requires-Dist: numpy==1.24.1
Requires-Dist: opencv-python==4.7.0.68
Requires-Dist: packaging==23.0
Requires-Dist: pandas==1.5.2
Requires-Dist: Pillow==9.4.0
Requires-Dist: pipreqs==0.4.11
Requires-Dist: pluggy==1.0.0
Requires-Dist: POT==0.9.5
Requires-Dist: psutil==5.9.4
Requires-Dist: pycodestyle==2.10.0
Requires-Dist: pyflakes==3.0.1
Requires-Dist: pyparsing==3.0.9
Requires-Dist: pytest==7.2.0
Requires-Dist: python-dateutil==2.8.2
Requires-Dist: pytz==2022.7
Requires-Dist: PyWavelets==1.4.1
Requires-Dist: requests==2.28.2
Requires-Dist: scikit-image==0.19.3
Requires-Dist: scikit-learn==1.2.2
Requires-Dist: scipy==1.10.0
Requires-Dist: six==1.16.0
Requires-Dist: tensorboard==2.12.0
Requires-Dist: tensorboardX==2.6
Requires-Dist: termcolor==2.2.0
Requires-Dist: threadpoolctl==3.1.0
Requires-Dist: tifffile==2022.10.10
Requires-Dist: tomli==2.0.1
Requires-Dist: tqdm==4.64.1
Requires-Dist: typing_extensions==4.4.0
Requires-Dist: urllib3==1.26.14
Requires-Dist: xgboost==1.7.4
Requires-Dist: yarg==0.1.9
Dynamic: license-file
